specarray/__init__.py
specarray/specarray.py
specarray/io/__init__.py
specarray/io/specim_folder.py
specarray-0.3.0.dist-info/LICENSE
specarray-0.3.0.dist-info/WHEEL
specarray-0.3.0.dist-info/METADATA
specarray-0.3.0.dist-info/RECORD
